tatukgis_pdk-110.0.40375.data/purelib/tatukgis_pdk/__init__.py
tatukgis_pdk-110.0.40375.data/purelib/tatukgis_pdk/__init__.pyi
tatukgis_pdk-110.0.40375.data/purelib/tatukgis_pdk/__version__.py
tatukgis_pdk-110.0.40375.data/purelib/tatukgis_pdk/_lib/win32/sk4d.dll
tatukgis_pdk-110.0.40375.data/purelib/tatukgis_pdk/_lib/win32/sqlite3.dll
tatukgis_pdk-110.0.40375.data/purelib/tatukgis_pdk/_lib/win32/tatukgis_pdk.pyd
tatukgis_pdk-110.0.40375.dist-info/LICENSE
tatukgis_pdk-110.0.40375.dist-info/METADATA
tatukgis_pdk-110.0.40375.dist-info/WHEEL
tatukgis_pdk-110.0.40375.dist-info/top_level.txt
tatukgis_pdk-110.0.40375.dist-info/RECORD
