Metadata-Version: 2.1
Name: tatukgis-pdk
Version: 110.0.40375
Summary: TatukGIS Developer Kernel for Python (DK.Python). A powerfull GIS SDK.
Home-page: https://tatukgis.com
Author: TatukGIS sp. z o.o.
Author-email: sales@tatukgis.com
License: Other/Proprietary License
Classifier: Intended Audience :: Developers
Classifier: Topic :: Software Development
Classifier: License :: Other/Proprietary License
Classifier: Programming Language :: Python :: 3
Classifier: Programming Language :: Python :: 3.8
Classifier: Programming Language :: Python :: 3.9
Classifier: Programming Language :: Python :: 3.10
Classifier: Programming Language :: Python :: 3.11
Classifier: Programming Language :: Python :: 3.12
Classifier: Programming Language :: Python :: 3.13
Classifier: Programming Language :: Python :: 3.14
Classifier: Programming Language :: Python :: 3 :: Only
Classifier: Operating System :: Microsoft :: Windows
Classifier: Operating System :: POSIX
Classifier: Operating System :: Unix
Classifier: Operating System :: MacOS
Classifier: Topic :: Scientific/Engineering :: GIS
Classifier: Topic :: Software Development :: Libraries :: Python Modules
Classifier: Topic :: Software Development :: User Interfaces
License-File: LICENSE
